{
  "formatVersion": 1,
  "database": {
    "version": 1,
    "identityHash": "5cb88e4455a7dbc9e3100a5bb09a2b9e",
    "entities": [
      {
        "tableName": "Article",
        "createSql": "CREATE TABLE IF NOT EXISTS `${TABLE_NAME}` (`id` INTEGER NOT NULL, `author` TEXT, `title` TEXT NOT NULL, `description` TEXT NOT NULL, `url` TEXT NOT NULL, `urlToImage` TEXT, `publishedAt` TEXT, `content` TEXT NOT NULL, `name` TEXT, PRIMARY KEY(`id`))",
        "fields": [
          {
            "fieldPath": "id",
            "columnName": "id",
            "affinity": "INTEGER",
            "notNull": true
          },
          {
            "fieldPath": "author",
            "columnName": "author",
            "affinity": "TEXT",
            "notNull": false
          },
          {
            "fieldPath": "title",
            "columnName": "title",
            "affinity": "TEXT",
            "notNull": true
          },
          {
            "fieldPath": "description",
            "columnName": "description",
            "affinity": "TEXT",
            "notNull": true
          },
          {
            "fieldPath": "url",
            "columnName": "url",
            "affinity": "TEXT",
            "notNull": true
          },
          {
            "fieldPath": "urlToImage",
            "columnName": "urlToImage",
            "affinity": "TEXT",
            "notNull": false
          },
          {
            "fieldPath": "publishedAt",
            "columnName": "publishedAt",
            "affinity": "TEXT",
            "notNull": false
          },
          {
            "fieldPath": "content",
            "columnName": "content",
            "affinity": "TEXT",
            "notNull": true
          },
          {
            "fieldPath": "source.name",
            "columnName": "name",
            "affinity": "TEXT",
            "notNull": false
          }
        ],
        "primaryKey": {
          "autoGenerate": false,
          "columnNames": [
            "id"
          ]
        },
        "indices": [],
        "foreignKeys": []
      }
    ],
    "views": [],
    "setupQueries": [
      "CREATE TABLE IF NOT EXISTS room_master_table (id INTEGER PRIMARY KEY,identity_hash TEXT)",
      "INSERT OR REPLACE INTO room_master_table (id,identity_hash) VALUES(42, '5cb88e4455a7dbc9e3100a5bb09a2b9e')"
    ]
  }
}